oarepo_health_check/__init__.py
oarepo_health_check/ext.py
oarepo_health_check/version.py
oarepo_health_check-1.0.2.dist-info/LICENSE
oarepo_health_check-1.0.2.dist-info/METADATA
oarepo_health_check-1.0.2.dist-info/WHEEL
oarepo_health_check-1.0.2.dist-info/entry_points.txt
oarepo_health_check-1.0.2.dist-info/top_level.txt
oarepo_health_check-1.0.2.dist-info/RECORD
